schema_compare_postgres/__init__.py
schema_compare_postgres/gerir_procedure.py
schema_compare_postgres/gerir_tabelas.py
schema_compare_postgres/main.py
schema_compare_postgres-0.0.1.dist-info/METADATA
schema_compare_postgres-0.0.1.dist-info/WHEEL
schema_compare_postgres-0.0.1.dist-info/top_level.txt
schema_compare_postgres-0.0.1.dist-info/RECORD
