Metadata-Version: 2.1
Name: schema-compare-postgres
Version: 0.0.1
Summary: Este pacote Python permite comparar estruturas de bancos de dados PostgresSQL, identificando diferenças entre tabelas, views, procedures e funções. Ideal para auditorias e sincronizações entre ambientes de banco de dados.
Home-page: https://github.com/Isaquemz/schema_compare_postgres.git
Author: Isaque Menezes
Author-email: isaquesantos1517@gmail.com
Requires-Python: >=3.8
Requires-Dist: psycopg2>=2.9.9
